pytie/__init__.py
pytie/functions.py
PyTie-4.0.2.dist-info/METADATA
PyTie-4.0.2.dist-info/WHEEL
PyTie-4.0.2.dist-info/top_level.txt
PyTie-4.0.2.dist-info/RECORD
