Metadata-Version: 2.1
Name: PyTie
Version: 4.0.2
Summary: Well tie in Python
Home-page: https://github.com/raquelsilva/pytie
Author: Raquel Theodoro Amancio da Silva
Author-email: ratheodoro@gmail.com
License: UNKNOWN
Platform: UNKNOWN
Classifier: Programming Language :: Python :: 3
Classifier: License :: OSI Approved :: MIT License
Classifier: Intended Audience :: Science/Research
Classifier: Intended Audience :: Developers
Classifier: Intended Audience :: Education
Classifier: Topic :: Software Development :: Libraries
Requires-Python: >=3.7
Requires-Dist: numpy
Requires-Dist: lasio
Requires-Dist: pandas
Requires-Dist: matplotlib
Requires-Dist: scipy
